{
  "meta": {
    "format_version": "5.0",
    "model_format": "java_block",
    "box_uv": true
  },
  "name": "custom_model",
  "parent": "",
  "java_block_version": "1.21.11",
  "ambientocclusion": true,
  "front_gui_light": false,
  "visible_box": [
    1,
    1,
    0
  ],
  "variable_placeholders": "",
  "multi_file_ruleset": "",
  "variable_placeholder_buttons": [],
  "unhandled_root_fields": {},
  "resolution": {
    "width": 128,
    "height": 128
  },
  "elements": [
    {
      "name": "Torso",
      "box_uv": true,
      "rescale": false,
      "locked": false,
      "from": [
        -4.0,
        11.0,
        -2.0
      ],
      "to": [
        3.0,
        24.0,
        2.0
      ],
      "autouv": 0,
      "color": 0,
      "origin": [
        -0.5,
        23.5,
        0.0
      ],
      "faces": {
        "north": {
          "uv": [
            5.0,
            2.0,
            12.0,
            15.0
          ],
          "texture": 0
        },
        "east": {
          "uv": [
            1,
            2.0,
            5.0,
            15.0
          ],
          "texture": 0
        },
        "south": {
          "uv": [
            16.0,
            2.0,
            23.0,
            15.0
          ],
          "texture": 0
        },
        "west": {
          "uv": [
            12.0,
            2.0,
            16.0,
            15.0
          ],
          "texture": 0
        },
        "up": {
          "uv": [
            12.0,
            2.0,
            5.0,
            -2
          ],
          "texture": 0
        },
        "down": {
          "uv": [
            19.0,
            -2,
            12.0,
            2.0
          ],
          "texture": 0
        }
      },
      "type": "cube",
      "uuid": "63acc51e-19cf-426e-ada4-287004fd80dd",
      "rotation": [
        -0.0,
        -179.999579,
        0.0
      ]
    },
    {
      "name": "RightLeg",
      "box_uv": true,
      "rescale": false,
      "locked": false,
      "from": [
        -0.0,
        0.0,
        0.0
      ],
      "to": [
        3.0,
        2.0,
        4.0
      ],
      "autouv": 0,
      "color": 0,
      "origin": [
        1.5,
        12.3302,
        0.258
      ],
      "faces": {
        "north": {
          "uv": [
            5.0,
            2.0,
            8.0,
            4.0
          ],
          "texture": 0
        },
        "east": {
          "uv": [
            1,
            2.0,
            5.0,
            4.0
          ],
          "texture": 0
        },
        "south": {
          "uv": [
            12.0,
            2.0,
            15.0,
            4.0
          ],
          "texture": 0
        },
        "west": {
          "uv": [
            8.0,
            2.0,
            12.0,
            4.0
          ],
          "texture": 0
        },
        "up": {
          "uv": [
            8.0,
            2.0,
            5.0,
            -2
          ],
          "texture": 0
        },
        "down": {
          "uv": [
            11.0,
            -2,
            8.0,
            2.0
          ],
          "texture": 0
        }
      },
      "type": "cube",
      "uuid": "4829851e-69b8-4e0a-b1ec-e796ec9e1185",
      "rotation": [
        -0.0,
        -179.999579,
        0.0
      ]
    },
    {
      "name": "cube_r1",
      "box_uv": true,
      "rescale": false,
      "locked": false,
      "from": [
        -0.0,
        6.0,
        0.0
      ],
      "to": [
        3.0,
        14.0,
        4.0
      ],
      "autouv": 0,
      "color": 0,
      "origin": [
        2.0,
        6.0,
        3.0
      ],
      "faces": {
        "north": {
          "uv": [
            5.0,
            2.0,
            8.0,
            10.0
          ],
          "texture": 0
        },
        "east": {
          "uv": [
            1,
            2.0,
            5.0,
            10.0
          ],
          "texture": 0
        },
        "south": {
          "uv": [
            12.0,
            2.0,
            15.0,
            10.0
          ],
          "texture": 0
        },
        "west": {
          "uv": [
            8.0,
            2.0,
            12.0,
            10.0
          ],
          "texture": 0
        },
        "up": {
          "uv": [
            8.0,
            2.0,
            5.0,
            -2
          ],
          "texture": 0
        },
        "down": {
          "uv": [
            11.0,
            -2,
            8.0,
            2.0
          ],
          "texture": 0
        }
      },
      "type": "cube",
      "uuid": "9609df8d-abc7-4f16-aabc-7ca8703ceb29",
      "rotation": [
        -15.000035,
        0.0,
        0.0
      ]
    },
    {
      "name": "cube_r2",
      "box_uv": true,
      "rescale": false,
      "locked": false,
      "from": [
        -0.0,
        4.0,
        -4.0
      ],
      "to": [
        3.0,
        6.0,
        1.0
      ],
      "autouv": 0,
      "color": 0,
      "origin": [
        1.0,
        4.0,
        0.0
      ],
      "faces": {
        "north": {
          "uv": [
            6.0,
            2.0,
            9.0,
            4.0
          ],
          "texture": 0
        },
        "east": {
          "uv": [
            1,
            2.0,
            6.0,
            4.0
          ],
          "texture": 0
        },
        "south": {
          "uv": [
            14.0,
            2.0,
            17.0,
            4.0
          ],
          "texture": 0
        },
        "west": {
          "uv": [
            9.0,
            2.0,
            14.0,
            4.0
          ],
          "texture": 0
        },
        "up": {
          "uv": [
            9.0,
            2.0,
            6.0,
            -3
          ],
          "texture": 0
        },
        "down": {
          "uv": [
            12.0,
            -3,
            9.0,
            2.0
          ],
          "texture": 0
        }
      },
      "type": "cube",
      "uuid": "21dbc69c-ef12-438a-b09e-b6e33cb0ae8d",
      "rotation": [
        125.002202,
        0.0,
        0.0
      ]
    },
    {
      "name": "cube_r3",
      "box_uv": true,
      "rescale": false,
      "locked": false,
      "from": [
        -0.0,
        1.0,
        -2.0
      ],
      "to": [
        3.0,
        3.0,
        1.0
      ],
      "autouv": 0,
      "color": 0,
      "origin": [
        1.0,
        1.0,
        0.0
      ],
      "faces": {
        "north": {
          "uv": [
            4.0,
            2.0,
            7.0,
            4.0
          ],
          "texture": 0
        },
        "east": {
          "uv": [
            1,
            2.0,
            4.0,
            4.0
          ],
          "texture": 0
        },
        "south": {
          "uv": [
            10.0,
            2.0,
            13.0,
            4.0
          ],
          "texture": 0
        },
        "west": {
          "uv": [
            7.0,
            2.0,
            10.0,
            4.0
          ],
          "texture": 0
        },
        "up": {
          "uv": [
            7.0,
            2.0,
            4.0,
            -1
          ],
          "texture": 0
        },
        "down": {
          "uv": [
            10.0,
            -1,
            7.0,
            2.0
          ],
          "texture": 0
        }
      },
      "type": "cube",
      "uuid": "5027139a-9e7e-4668-81c8-29940780cb9f",
      "rotation": [
        45.000105,
        0.0,
        0.0
      ]
    },
    {
      "name": "LeftLeg",
      "box_uv": true,
      "rescale": false,
      "locked": false,
      "from": [
        -4.0,
        0.0,
        -2.0
      ],
      "to": [
        -1.0,
        2.0,
        2.0
      ],
      "autouv": 0,
      "color": 0,
      "origin": [
        -2.5,
        12.3625,
        -0.6213
      ],
      "faces": {
        "north": {
          "uv": [
            5.0,
            2.0,
            8.0,
            4.0
          ],
          "texture": 0
        },
        "east": {
          "uv": [
            1,
            2.0,
            5.0,
            4.0
          ],
          "texture": 0
        },
        "south": {
          "uv": [
            12.0,
            2.0,
            15.0,
            4.0
          ],
          "texture": 0
        },
        "west": {
          "uv": [
            8.0,
            2.0,
            12.0,
            4.0
          ],
          "texture": 0
        },
        "up": {
          "uv": [
            8.0,
            2.0,
            5.0,
            -2
          ],
          "texture": 0
        },
        "down": {
          "uv": [
            11.0,
            -2,
            8.0,
            2.0
          ],
          "texture": 0
        }
      },
      "type": "cube",
      "uuid": "952794a0-653c-4e4e-9a83-e42e6892a6bd",
      "rotation": [
        -0.0,
        -179.999579,
        0.0
      ]
    },
    {
      "name": "cube_r4",
      "box_uv": true,
      "rescale": false,
      "locked": false,
      "from": [
        -4.0,
        6.0,
        -1.0
      ],
      "to": [
        -1.0,
        14.0,
        2.0
      ],
      "autouv": 0,
      "color": 0,
      "origin": [
        -2.0,
        6.0,
        1.0
      ],
      "faces": {
        "north": {
          "uv": [
            4.0,
            2.0,
            7.0,
            10.0
          ],
          "texture": 0
        },
        "east": {
          "uv": [
            1,
            2.0,
            4.0,
            10.0
          ],
          "texture": 0
        },
        "south": {
          "uv": [
            10.0,
            2.0,
            13.0,
            10.0
          ],
          "texture": 0
        },
        "west": {
          "uv": [
            7.0,
            2.0,
            10.0,
            10.0
          ],
          "texture": 0
        },
        "up": {
          "uv": [
            7.0,
            2.0,
            4.0,
            -1
          ],
          "texture": 0
        },
        "down": {
          "uv": [
            10.0,
            -1,
            7.0,
            2.0
          ],
          "texture": 0
        }
      },
      "type": "cube",
      "uuid": "9326f353-0721-444a-b947-b9e6a39f815d",
      "rotation": [
        -15.000035,
        0.0,
        0.0
      ]
    },
    {
      "name": "cube_r5",
      "box_uv": true,
      "rescale": false,
      "locked": false,
      "from": [
        -4.0,
        4.0,
        -6.0
      ],
      "to": [
        -1.0,
        6.0,
        -1.0
      ],
      "autouv": 0,
      "color": 0,
      "origin": [
        -3.0,
        4.0,
        -2.0
      ],
      "faces": {
        "north": {
          "uv": [
            6.0,
            2.0,
            9.0,
            4.0
          ],
          "texture": 0
        },
        "east": {
          "uv": [
            1,
            2.0,
            6.0,
            4.0
          ],
          "texture": 0
        },
        "south": {
          "uv": [
            14.0,
            2.0,
            17.0,
            4.0
          ],
          "texture": 0
        },
        "west": {
          "uv": [
            9.0,
            2.0,
            14.0,
            4.0
          ],
          "texture": 0
        },
        "up": {
          "uv": [
            9.0,
            2.0,
            6.0,
            -3
          ],
          "texture": 0
        },
        "down": {
          "uv": [
            12.0,
            -3,
            9.0,
            2.0
          ],
          "texture": 0
        }
      },
      "type": "cube",
      "uuid": "0135c5e0-e4f4-4a0a-ba78-1387ef44fcff",
      "rotation": [
        125.002202,
        0.0,
        0.0
      ]
    },
    {
      "name": "cube_r6",
      "box_uv": true,
      "rescale": false,
      "locked": false,
      "from": [
        -4.0,
        1.0,
        -4.0
      ],
      "to": [
        -1.0,
        3.0,
        -1.0
      ],
      "autouv": 0,
      "color": 0,
      "origin": [
        -3.0,
        1.0,
        -2.0
      ],
      "faces": {
        "north": {
          "uv": [
            4.0,
            2.0,
            7.0,
            4.0
          ],
          "texture": 0
        },
        "east": {
          "uv": [
            1,
            2.0,
            4.0,
            4.0
          ],
          "texture": 0
        },
        "south": {
          "uv": [
            10.0,
            2.0,
            13.0,
            4.0
          ],
          "texture": 0
        },
        "west": {
          "uv": [
            7.0,
            2.0,
            10.0,
            4.0
          ],
          "texture": 0
        },
        "up": {
          "uv": [
            7.0,
            2.0,
            4.0,
            -1
          ],
          "texture": 0
        },
        "down": {
          "uv": [
            10.0,
            -1,
            7.0,
            2.0
          ],
          "texture": 0
        }
      },
      "type": "cube",
      "uuid": "e129e7fa-14d7-4cda-896e-4d4df1188598",
      "rotation": [
        45.000105,
        0.0,
        0.0
      ]
    },
    {
      "name": "Head",
      "box_uv": true,
      "rescale": false,
      "locked": false,
      "from": [
        -4.0,
        24.0,
        -4.0
      ],
      "to": [
        3.0,
        31.0,
        4.0
      ],
      "autouv": 0,
      "color": 0,
      "origin": [
        -0.5,
        24.5,
        0.0
      ],
      "faces": {
        "north": {
          "uv": [
            9.0,
            2.0,
            16.0,
            9.0
          ],
          "texture": 0
        },
        "east": {
          "uv": [
            1,
            2.0,
            9.0,
            9.0
          ],
          "texture": 0
        },
        "south": {
          "uv": [
            24.0,
            2.0,
            31.0,
            9.0
          ],
          "texture": 0
        },
        "west": {
          "uv": [
            16.0,
            2.0,
            24.0,
            9.0
          ],
          "texture": 0
        },
        "up": {
          "uv": [
            16.0,
            2.0,
            9.0,
            -6
          ],
          "texture": 0
        },
        "down": {
          "uv": [
            23.0,
            -6,
            16.0,
            2.0
          ],
          "texture": 0
        }
      },
      "type": "cube",
      "uuid": "e876a15b-3198-4bf7-9a78-99a8c384e366",
      "rotation": [
        -0.0,
        -179.999579,
        0.0
      ]
    },
    {
      "name": "RightArm",
      "box_uv": true,
      "rescale": false,
      "locked": false,
      "from": [
        -1.0,
        14.0,
        -2.0
      ],
      "to": [
        2.0,
        24.0,
        2.0
      ],
      "autouv": 0,
      "color": 0,
      "origin": [
        2.5,
        22.0,
        0.0
      ],
      "faces": {
        "north": {
          "uv": [
            5.0,
            2.0,
            8.0,
            12.0
          ],
          "texture": 0
        },
        "east": {
          "uv": [
            1,
            2.0,
            5.0,
            12.0
          ],
          "texture": 0
        },
        "south": {
          "uv": [
            12.0,
            2.0,
            15.0,
            12.0
          ],
          "texture": 0
        },
        "west": {
          "uv": [
            8.0,
            2.0,
            12.0,
            12.0
          ],
          "texture": 0
        },
        "up": {
          "uv": [
            8.0,
            2.0,
            5.0,
            -2
          ],
          "texture": 0
        },
        "down": {
          "uv": [
            11.0,
            -2,
            8.0,
            2.0
          ],
          "texture": 0
        }
      },
      "type": "cube",
      "uuid": "21c071d8-a518-46d9-a019-1fbc3d04e8f1",
      "rotation": [
        -0.0,
        -179.999579,
        0.0
      ]
    },
    {
      "name": "LeftArm",
      "box_uv": true,
      "rescale": false,
      "locked": false,
      "from": [
        -3.0,
        14.0,
        -2.0
      ],
      "to": [
        -0.0,
        24.0,
        2.0
      ],
      "autouv": 0,
      "color": 0,
      "origin": [
        -3.5,
        22.0,
        0.0
      ],
      "faces": {
        "north": {
          "uv": [
            5.0,
            2.0,
            8.0,
            12.0
          ],
          "texture": 0
        },
        "east": {
          "uv": [
            1,
            2.0,
            5.0,
            12.0
          ],
          "texture": 0
        },
        "south": {
          "uv": [
            12.0,
            2.0,
            15.0,
            12.0
          ],
          "texture": 0
        },
        "west": {
          "uv": [
            8.0,
            2.0,
            12.0,
            12.0
          ],
          "texture": 0
        },
        "up": {
          "uv": [
            8.0,
            2.0,
            5.0,
            -2
          ],
          "texture": 0
        },
        "down": {
          "uv": [
            11.0,
            -2,
            8.0,
            2.0
          ],
          "texture": 0
        }
      },
      "type": "cube",
      "uuid": "d63d9648-f70e-416a-a388-7b43ee4d06ac",
      "rotation": [
        -0.0,
        -179.999579,
        0.0
      ]
    }
  ],
  "outliner": [
    {
      "name": "Torso",
      "origin": [
        -0.5,
        23.0,
        0.0
      ],
      "color": 0,
      "uuid": "811a06bd-e742-4490-8083-7cecacdcf2a0",
      "export": true,
      "mirror_uv": false,
      "isOpen": true,
      "locked": false,
      "visibility": true,
      "autouv": 0,
      "children": [
        "63acc51e-19cf-426e-ada4-287004fd80dd"
      ]
    },
    {
      "name": "RightLeg",
      "origin": [
        1.5,
        12.3302,
        0.258
      ],
      "color": 0,
      "uuid": "208817e9-2c74-4a82-b0ac-55a8b26d72df",
      "export": true,
      "mirror_uv": false,
      "isOpen": true,
      "locked": false,
      "visibility": true,
      "autouv": 0,
      "children": [
        "4829851e-69b8-4e0a-b1ec-e796ec9e1185",
        {
          "name": "cube_r1",
          "origin": [
            2.0,
            6.0,
            3.0
          ],
          "color": 0,
          "uuid": "e7f7163c-41ca-41b5-b8a0-f0163caaf151",
          "export": true,
          "mirror_uv": false,
          "isOpen": true,
          "locked": false,
          "visibility": true,
          "autouv": 0,
          "children": [
            "9609df8d-abc7-4f16-aabc-7ca8703ceb29"
          ]
        },
        {
          "name": "cube_r2",
          "origin": [
            1.0,
            4.0,
            0.0
          ],
          "color": 0,
          "uuid": "678348eb-bfce-4246-9865-25f4a5398497",
          "export": true,
          "mirror_uv": false,
          "isOpen": true,
          "locked": false,
          "visibility": true,
          "autouv": 0,
          "children": [
            "21dbc69c-ef12-438a-b09e-b6e33cb0ae8d"
          ]
        },
        {
          "name": "cube_r3",
          "origin": [
            1.0,
            1.0,
            0.0
          ],
          "color": 0,
          "uuid": "2ab25721-424e-4ba3-a850-b6b2805c8560",
          "export": true,
          "mirror_uv": false,
          "isOpen": true,
          "locked": false,
          "visibility": true,
          "autouv": 0,
          "children": [
            "5027139a-9e7e-4668-81c8-29940780cb9f"
          ]
        }
      ]
    },
    {
      "name": "LeftLeg",
      "origin": [
        -2.5,
        12.3625,
        -0.6213
      ],
      "color": 0,
      "uuid": "035bccaf-ca72-498b-99d4-c7ae315bc480",
      "export": true,
      "mirror_uv": false,
      "isOpen": true,
      "locked": false,
      "visibility": true,
      "autouv": 0,
      "children": [
        "952794a0-653c-4e4e-9a83-e42e6892a6bd",
        {
          "name": "cube_r4",
          "origin": [
            -2.0,
            6.0,
            1.0
          ],
          "color": 0,
          "uuid": "b56f2723-728d-45e7-9e17-bf8e32f89987",
          "export": true,
          "mirror_uv": false,
          "isOpen": true,
          "locked": false,
          "visibility": true,
          "autouv": 0,
          "children": [
            "9326f353-0721-444a-b947-b9e6a39f815d"
          ]
        },
        {
          "name": "cube_r5",
          "origin": [
            -3.0,
            4.0,
            -2.0
          ],
          "color": 0,
          "uuid": "ddf7329c-3299-46c4-9f5c-8a245b337263",
          "export": true,
          "mirror_uv": false,
          "isOpen": true,
          "locked": false,
          "visibility": true,
          "autouv": 0,
          "children": [
            "0135c5e0-e4f4-4a0a-ba78-1387ef44fcff"
          ]
        },
        {
          "name": "cube_r6",
          "origin": [
            -3.0,
            1.0,
            -2.0
          ],
          "color": 0,
          "uuid": "a844dbf5-f2ee-44b8-aa78-79f9d46ce4e4",
          "export": true,
          "mirror_uv": false,
          "isOpen": true,
          "locked": false,
          "visibility": true,
          "autouv": 0,
          "children": [
            "e129e7fa-14d7-4cda-896e-4d4df1188598"
          ]
        }
      ]
    },
    {
      "name": "Head",
      "origin": [
        -0.5,
        24.0,
        0.0
      ],
      "color": 0,
      "uuid": "d286da32-24a1-4486-b989-09ba83dc9e4b",
      "export": true,
      "mirror_uv": false,
      "isOpen": true,
      "locked": false,
      "visibility": true,
      "autouv": 0,
      "children": [
        "e876a15b-3198-4bf7-9a78-99a8c384e366"
      ]
    },
    {
      "name": "RightArm",
      "origin": [
        2.5,
        22.0,
        0.0
      ],
      "color": 0,
      "uuid": "1fabb528-3a6b-4168-94a0-a543b6b91393",
      "export": true,
      "mirror_uv": false,
      "isOpen": true,
      "locked": false,
      "visibility": true,
      "autouv": 0,
      "children": [
        "21c071d8-a518-46d9-a019-1fbc3d04e8f1"
      ]
    },
    {
      "name": "LeftArm",
      "origin": [
        -3.5,
        22.0,
        0.0
      ],
      "color": 0,
      "uuid": "eb59e570-dc3e-4ac7-bd41-c74ee05435f2",
      "export": true,
      "mirror_uv": false,
      "isOpen": true,
      "locked": false,
      "visibility": true,
      "autouv": 0,
      "children": [
        "d63d9648-f70e-416a-a388-7b43ee4d06ac"
      ]
    }
  ]
}
